Elysium/__init__.py
Elysium/elysium.py
elysium_knowledge_repository-0.0.1.dist-info/LICENSE
elysium_knowledge_repository-0.0.1.dist-info/METADATA
elysium_knowledge_repository-0.0.1.dist-info/WHEEL
elysium_knowledge_repository-0.0.1.dist-info/top_level.txt
elysium_knowledge_repository-0.0.1.dist-info/RECORD
